AvatarsGenerator/__init__.py
AvatarsGenerator/generator.py
AvatarsGenerator/parts/__init__.py
AvatarsGenerator/parts/body.py
AvatarsGenerator/parts/colors.py
AvatarsGenerator/parts/face.py
AvatarsGenerator/parts/Clothing/BlazerShirt.py
AvatarsGenerator/parts/Clothing/BlazerSweater.py
AvatarsGenerator/parts/Clothing/CollarSweater.py
AvatarsGenerator/parts/Clothing/Hoodie.py
AvatarsGenerator/parts/Clothing/Overall.py
AvatarsGenerator/parts/Clothing/Shirt.py
AvatarsGenerator/parts/Clothing/ShirtCrewNeck.py
AvatarsGenerator/parts/Clothing/ShirtScoopNeck.py
AvatarsGenerator/parts/Clothing/ShirtVNeck.py
AvatarsGenerator/parts/Clothing/__init__.py
AvatarsGenerator/parts/Clothing/Graphic/Bat.py
AvatarsGenerator/parts/Clothing/Graphic/Bear.py
AvatarsGenerator/parts/Clothing/Graphic/Cumbia.py
AvatarsGenerator/parts/Clothing/Graphic/Deer.py
AvatarsGenerator/parts/Clothing/Graphic/Diamond.py
AvatarsGenerator/parts/Clothing/Graphic/Hola.py
AvatarsGenerator/parts/Clothing/Graphic/Pizza.py
AvatarsGenerator/parts/Clothing/Graphic/Resist.py
AvatarsGenerator/parts/Clothing/Graphic/Selena.py
AvatarsGenerator/parts/Clothing/Graphic/Skull.py
AvatarsGenerator/parts/Clothing/Graphic/SkullOutline.py
AvatarsGenerator/parts/Clothing/Graphic/__init__.py
AvatarsGenerator/parts/Eyebrow/Angry.py
AvatarsGenerator/parts/Eyebrow/AngryNatural.py
AvatarsGenerator/parts/Eyebrow/Default.py
AvatarsGenerator/parts/Eyebrow/DefaultNatural.py
AvatarsGenerator/parts/Eyebrow/FlatNatural.py
AvatarsGenerator/parts/Eyebrow/FrownNatural.py
AvatarsGenerator/parts/Eyebrow/RaisedExcited.py
AvatarsGenerator/parts/Eyebrow/RaisedExcitedNatural.py
AvatarsGenerator/parts/Eyebrow/SadConcerned.py
AvatarsGenerator/parts/Eyebrow/SadConcernedNatural.py
AvatarsGenerator/parts/Eyebrow/UpDown.py
AvatarsGenerator/parts/Eyebrow/UpDownNatural.py
AvatarsGenerator/parts/Eyebrow/__init__.py
AvatarsGenerator/parts/Eyes/Closed.py
AvatarsGenerator/parts/Eyes/Cry.py
AvatarsGenerator/parts/Eyes/Default.py
AvatarsGenerator-0.0.4.dist-info/LICENSE
AvatarsGenerator-0.0.4.dist-info/METADATA
AvatarsGenerator-0.0.4.dist-info/WHEEL
AvatarsGenerator-0.0.4.dist-info/top_level.txt
AvatarsGenerator-0.0.4.dist-info/RECORD
