Metadata-Version: 2.1
Name: AvatarsGenerator
Version: 0.0.4
Summary: Random avatars generator
Home-page: https://github.com/y0gurt-dv/AvatarsGenerator
Author: y0gurt-dv
Author-email: <sigirt3@gmail.com>
License: UNKNOWN
Keywords: python,avatars,random,random avatars,generator,avatars generator
Platform: UNKNOWN
License-File: LICENSE
Requires-Dist: wand
